.flake8
.gitignore
.pre-commit-config.yaml
.readthedocs.yml
AUTHORS.rst
CONTRIBUTING.rst
HISTORY.rst
LICENSE
MANIFEST.in
README.md
pyproject.toml
.github/dependabot.yml
.github/workflows/publish.yml
ci/requirements/docs.yaml
ci/requirements/environment.yaml
docs/Makefile
docs/authors.rst
docs/conf.py
docs/contributing.rst
docs/history.rst
docs/index.rst
docs/installation.rst
docs/make.bat
docs/readme.rst
docs/usage.rst
slcwindinversion/__init__.py
slcwindinversion/cli.py
slcwindinversion/mainslcwindinversion.py
slcwindinversion/utils.py
slcwindinversion.egg-info/PKG-INFO
slcwindinversion.egg-info/SOURCES.txt
slcwindinversion.egg-info/dependency_links.txt
slcwindinversion.egg-info/entry_points.txt
slcwindinversion.egg-info/requires.txt
slcwindinversion.egg-info/top_level.txt
tests/__init__.py
tests/test_output_name.py
tests/test_slcwindinversion.py