Metadata-Version: 2.1
Name: slcwindinversion
Version: 2024.2.post1
Summary: Python library to generate Level-2 wind speed products from intermediate Sentinel-1 TOPS SLC-derived products.
Author: Antoine Grouazel
License: MIT
Keywords: SAR,windspeed,reseach,SAR,Sentinel-1
Classifier: Programming Language :: Python :: 3
Requires-Python: >=3.9
License-File: LICENSE
License-File: AUTHORS.rst
Requires-Dist: scipy
Requires-Dist: xsarsea
Requires-Dist: xarray
Requires-Dist: h5netcdf
Requires-Dist: xarray-datatree
Requires-Dist: importlib_resources
Requires-Dist: tqdm
